{
  "VahidOOnLine": 247798,
  "mwarmonitor": 11657,
  "pm_afshaa": 95025,
  "iaghapour": 2717,
  "DEJradio": 6046,
  "mamlekate": 103783,
  "VahidOnline": 76733,
  "kianmeli1": 88226,
  "IranIntlTV": 344852,
  "FoxNewsChannel": 3,
  "Shin_Persian": 7286,
  "Iliaen": 4506,
  "CnnBrk": 247615,
  "reutersworldchannel": 151527,
  "ManotoTV": 106264,
  "FarsiVOA": 222148,
  "DW_Farsi": 126622,
  "Persian_Trend_Official": 18286,
  "RadioFarda": 158863,
  "IranianMinds": 23474,
  "BBCPersian": 285305,
  "IranWire": 65,
  "idfinfarsi": 11922,
  "Dirty_Kids": 393353,
  "Hranews": 113898,
  "officialrezapahlavi": 1849,
  "configx2ray": 38663,
  "manototv": 106264,
  "alonews": 130776,
  "farsi_fox_news": 89200,
  "FoxNewsTwitter": 343545,
  "CNNfarsiCHANNEL": 51273,
  "WithYashar": 16117
}