{
  "VahidOOnLine": 245101,
  "mwarmonitor": 10755,
  "pm_afshaa": 93671,
  "iaghapour": 2669,
  "DEJradio": 5604,
  "mamlekate": 103684,
  "VahidOnline": 76257,
  "kianmeli1": 87957,
  "IranIntlTV": 341841,
  "FoxNewsChannel": 3,
  "Shin_Persian": 6970,
  "Iliaen": 4478,
  "CnnBrk": 247615,
  "reutersworldchannel": 151527,
  "ManotoTV": 106025,
  "FarsiVOA": 220460,
  "DW_Farsi": 125848,
  "Persian_Trend_Official": 16830,
  "RadioFarda": 158205,
  "IranianMinds": 22368,
  "BBCPersian": 283534,
  "IranWire": 65,
  "idfinfarsi": 11838,
  "Dirty_Kids": 391772,
  "Hranews": 113549,
  "officialrezapahlavi": 1844,
  "configx2ray": 38663,
  "manototv": 106025,
  "alonews": 127316,
  "farsi_fox_news": 89200,
  "FoxNewsTwitter": 342891,
  "CNNfarsiCHANNEL": 51273,
  "WithYashar": 14600
}