{
  "VahidOOnLine": 247781,
  "mwarmonitor": 11649,
  "pm_afshaa": 95009,
  "iaghapour": 2717,
  "DEJradio": 6044,
  "mamlekate": 103783,
  "VahidOnline": 76733,
  "kianmeli1": 88223,
  "IranIntlTV": 344829,
  "FoxNewsChannel": 3,
  "Shin_Persian": 7273,
  "Iliaen": 4506,
  "CnnBrk": 247615,
  "reutersworldchannel": 151527,
  "ManotoTV": 106264,
  "FarsiVOA": 222140,
  "DW_Farsi": 126608,
  "Persian_Trend_Official": 18268,
  "RadioFarda": 158861,
  "IranianMinds": 23457,
  "BBCPersian": 285300,
  "IranWire": 65,
  "idfinfarsi": 11922,
  "Dirty_Kids": 393345,
  "Hranews": 113892,
  "officialrezapahlavi": 1849,
  "configx2ray": 38663,
  "manototv": 106264,
  "alonews": 130735,
  "farsi_fox_news": 89200,
  "FoxNewsTwitter": 343540,
  "CNNfarsiCHANNEL": 51273,
  "WithYashar": 16092
}