{
  "VahidOOnLine": 247345,
  "mwarmonitor": 11515,
  "pm_afshaa": 94799,
  "iaghapour": 2706,
  "DEJradio": 5972,
  "mamlekate": 103762,
  "VahidOnline": 76667,
  "kianmeli1": 88171,
  "IranIntlTV": 344358,
  "FoxNewsChannel": 3,
  "Shin_Persian": 7200,
  "Iliaen": 4505,
  "CnnBrk": 247615,
  "reutersworldchannel": 151527,
  "ManotoTV": 106234,
  "FarsiVOA": 221881,
  "DW_Farsi": 126457,
  "Persian_Trend_Official": 18032,
  "RadioFarda": 158756,
  "IranianMinds": 23288,
  "BBCPersian": 285039,
  "IranWire": 65,
  "idfinfarsi": 11911,
  "Dirty_Kids": 393097,
  "Hranews": 113843,
  "officialrezapahlavi": 1846,
  "configx2ray": 38663,
  "manototv": 106234,
  "alonews": 130237,
  "farsi_fox_news": 89200,
  "FoxNewsTwitter": 343429,
  "CNNfarsiCHANNEL": 51273,
  "WithYashar": 15813
}