{
  "VahidOOnLine": 248043,
  "mwarmonitor": 11771,
  "pm_afshaa": 95125,
  "iaghapour": 2723,
  "DEJradio": 6094,
  "mamlekate": 103784,
  "VahidOnline": 76758,
  "kianmeli1": 88241,
  "IranIntlTV": 345159,
  "FoxNewsChannel": 3,
  "Shin_Persian": 7310,
  "Iliaen": 4508,
  "CnnBrk": 247615,
  "reutersworldchannel": 151527,
  "ManotoTV": 106277,
  "FarsiVOA": 222334,
  "DW_Farsi": 126719,
  "Persian_Trend_Official": 18419,
  "RadioFarda": 158936,
  "IranianMinds": 23583,
  "BBCPersian": 285440,
  "IranWire": 65,
  "idfinfarsi": 11942,
  "Dirty_Kids": 393501,
  "Hranews": 113949,
  "officialrezapahlavi": 1849,
  "configx2ray": 38663,
  "manototv": 106277,
  "alonews": 131145,
  "farsi_fox_news": 89200,
  "FoxNewsTwitter": 343631,
  "CNNfarsiCHANNEL": 51273,
  "WithYashar": 16228
}